setup.py
GroupmeChatbot/__init__.py
GroupmeChatbot/__main__.py
GroupmeChatbot/bot.py
GroupmeChatbot/server.py
GroupmeChatbot.egg-info/PKG-INFO
GroupmeChatbot.egg-info/SOURCES.txt
GroupmeChatbot.egg-info/dependency_links.txt
GroupmeChatbot.egg-info/not-zip-safe
GroupmeChatbot.egg-info/requires.txt
GroupmeChatbot.egg-info/top_level.txt