Metadata-Version: 1.0
Name: GroupmeChatbot
Version: 3.0.0
Summary: A Bot that responds with custom messages when mentioned in a Groupme chat
Home-page: https://github.com/dgisolfi/GroupmeChatbot
Author: dgisolfi
Author-email: UNKNOWN
License: MIT
Platform: UNKNOWN
